{
  "sources": [
    {
      "id": "nguoi-choi-khac-kim--0",
      "name": "Thuyet Minh #1",
      "contents": [
        {
          "id": "nguoi-choi-khac-kim--0",
          "name": "",
          "grid_number": 3,
          "streams": [
            {
              "id": "nguoi-choi-khac-kim--0-0",
              "name": "25",
              "stream_links": [
                {
                  "id": "nguoi-choi-khac-kim--0-0-0",
                  "name": "Link 1",
                  "type": "error",
                  "default": true,
                  "url": "error:no_stream"
                }
              ]
            },
            {
              "id": "nguoi-choi-khac-kim--0-1",
              "name": "24",
              "stream_links": [
                {
                  "id": "nguoi-choi-khac-kim--0-1-0",
                  "name": "Link 1",
                  "type": "error",
                  "default": true,
                  "url": "error:no_stream"
                }
              ]
            },
            {
              "id": "nguoi-choi-khac-kim--0-2",
              "name": "23",
              "stream_links": [
                {
                  "id": "nguoi-choi-khac-kim--0-2-0",
                  "name": "Link 1",
                  "type": "error",
                  "default": true,
                  "url": "error:no_stream"
                }
              ]
            },
            {
              "id": "nguoi-choi-khac-kim--0-3",
              "name": "22",
              "stream_links": [
                {
                  "id": "nguoi-choi-khac-kim--0-3-0",
                  "name": "Link 1",
                  "type": "error",
                  "default": true,
                  "url": "error:no_stream"
                }
              ]
            },
            {
              "id": "nguoi-choi-khac-kim--0-4",
              "name": "21",
              "stream_links": [
                {
                  "id": "nguoi-choi-khac-kim--0-4-0",
                  "name": "Link 1",
                  "type": "error",
                  "default": true,
                  "url": "error:no_stream"
                }
              ]
            }
          ]
        }
      ]
    }
  ],
  "subtitle": "Thuyet Minh",
  "search": "nguoi-choi-khac-kim cn animation hhkungfu hài hước hiện đại xem phim người chơi khắc kim thuyết minh: trong thế giới tương lai, trò chơi thực tế ảo \"kỷ nguyên\" do tập đoàn sở thị phát triển đã thu hút sự chú ý của toàn thế giới nhờ trải nghiệm nhập vai hoàn hảo. thế nhưng ngay trước ngày trò chơi ch... nguoi choi khac kim hoạt hình trung quốc thuyết minh anime donghua",
  "tags": [
    "CN Animation",
    "HHKungFu",
    "Hài Hước",
    "Hiện Đại"
  ],
  "genres": [
    "cn-animation",
    "hhkungfu",
    "hai-huoc",
    "hien-dai"
  ],
  "description": "Xem phim Người Chơi Khắc Kim Thuyết Minh: Trong thế giới tương lai, trò chơi thực tế ảo \"Kỷ Nguyên\" do Tập đoàn Sở thị phát triển đã thu hút sự chú ý của toàn thế giới nhờ trải nghiệm nhập vai hoàn hảo. Thế nhưng ngay trước ngày trò chơi ch..."
}